odoo/addons/server_environment_data_encryption/README.rst
odoo/addons/server_environment_data_encryption/__init__.py
odoo/addons/server_environment_data_encryption/__manifest__.py
odoo/addons/server_environment_data_encryption/i18n/ca.po
odoo/addons/server_environment_data_encryption/i18n/server_environment_data_encryption.pot
odoo/addons/server_environment_data_encryption/models/__init__.py
odoo/addons/server_environment_data_encryption/models/server_env_mixin.py
odoo/addons/server_environment_data_encryption/readme/CONFIGURE.rst
odoo/addons/server_environment_data_encryption/readme/CONTRIBUTORS.rst
odoo/addons/server_environment_data_encryption/readme/DESCRIPTION.rst
odoo/addons/server_environment_data_encryption/static/description/icon.png
odoo/addons/server_environment_data_encryption/static/description/index.html
odoo/addons/server_environment_data_encryption/tests/__init__.py
odoo/addons/server_environment_data_encryption/tests/test_server_environment_data_encrypt.py
odoo/addons/server_environment_data_encryption/tests/fixtures/base.xml
odoo/addons/server_environment_data_encryption/tests/fixtures/res1.xml
odoo/addons/server_environment_data_encryption/tests/fixtures/res2.xml
odoo14_addon_server_environment_data_encryption-14.0.1.0.2.dist-info/METADATA
odoo14_addon_server_environment_data_encryption-14.0.1.0.2.dist-info/WHEEL
odoo14_addon_server_environment_data_encryption-14.0.1.0.2.dist-info/top_level.txt
odoo14_addon_server_environment_data_encryption-14.0.1.0.2.dist-info/RECORD
